hlid-0.2.2.dist-info/METADATA
hlid-0.2.2.dist-info/WHEEL
hlid-0.2.2.dist-info/entry_points.txt
hlid-0.2.2.dist-info/licenses/LICENSE
hlid/__init__.py
hlid/py.typed
hlid-0.2.2.dist-info/RECORD
