Metadata-Version: 2.1
Name: hlid
Version: 0.2.2
Summary: HLID: a Human Lexicographically (sortable) Identifier
Keywords: HLID,UUID,ULID,Sortable
Author-Email: Nicholas de Jong <ndejong@threatpatrols.com>
License: MIT
Classifier: Intended Audience :: Developers
Classifier: License :: OSI Approved :: MIT License
Classifier: Programming Language :: Python :: 3
Project-URL: Bug Tracker, https://github.com/threatpatrols/hlid/issues
Project-URL: Documentation, https://github.com/threatpatrols/hlid
Project-URL: Homepage, https://pypi.python.org/pypi/hlid/
Project-URL: Repository, https://github.com/threatpatrols/hlid
Requires-Python: <4,>=3.8
Requires-Dist: typing>=3.0
